accuracy/__init__.py
accuracy/verify_box.py
verify_box-0.0.1.dist-info/METADATA
verify_box-0.0.1.dist-info/WHEEL
verify_box-0.0.1.dist-info/top_level.txt
verify_box-0.0.1.dist-info/RECORD
